dooray/__init__.py
dooray/dooray.py
dooray-0.0.23.dist-info/METADATA
dooray-0.0.23.dist-info/WHEEL
dooray-0.0.23.dist-info/top_level.txt
dooray-0.0.23.dist-info/RECORD
