Metadata-Version: 2.1
Name: dooray
Version: 0.0.23
Summary: dooray api
Home-page: https://github.com/mskim8717/dooray
Author: minsoo.kim
Author-email: ms.kim8717@gmail.com
License: MIT
Keywords: dooray,pydooray,python tutorial,pypi
Classifier: Programming Language :: Python :: 3.6
Classifier: Programming Language :: Python :: 3.7
Classifier: Programming Language :: Python :: 3.8
Classifier: Programming Language :: Python :: 3.9
Classifier: Programming Language :: Python :: 3.10
Requires-Python: >=3.6
Requires-Dist: requests
